{
  "track": [
    { "id": 1,
     "name": "HeartBreak Weather" ,
     "owner":[
       {"id":7879,
       "name":"Nial Horran"
       }
       ] ,
     "images":"https://i.scdn.co/image/ab67616d0000b2733d13e91ce05c4e9b3e7201b7",
      "tracks":[
     {
     "href":"google.com",
      "total":"1" 
     }
     ]
    },
     { "id": 2,
     "name": "HeartBreak Weather" ,
     "owner":[
       {"id":7879,
       "name":"Nial Horran"
       }
       ] ,
     "images":"https://i.scdn.co/image/ab67616d0000b2733d13e91ce05c4e9b3e7201b7",
      "tracks":[
     {
     "href":"google.com",
      "total":"1" 
     }
     ]
    },
     { "id": 3,
     "name": "HeartBreak Weather" ,
     "owner":[
       {"id":7879,
       "name":"Nial Horran"
       }
       ] ,
     "images":"https://i.scdn.co/image/ab67616d0000b2733d13e91ce05c4e9b3e7201b7",
      "tracks":[
     {
     "href":"google.com",
      "total":"1" 
     }
     ]
    },
     { "id": 4,
     "name": "HeartBreak Weather" ,
     "owner":[
       {"id":7879,
       "name":"Nial Horran"
       }
       ] ,
     "images":"https://i.scdn.co/image/ab67616d0000b2733d13e91ce05c4e9b3e7201b7",
      "tracks":[
     {
     "href":"google.com",
      "total":"1" 
     }
     ]
    },
     { "id": 5,
     "name": "HeartBreak Weather" ,
     "owner":[
       {"id":7879,
       "name":"Nial Horran"
       }
       ] ,
     "images":"https://i.scdn.co/image/ab67616d0000b2733d13e91ce05c4e9b3e7201b7",
      "tracks":[
     {
     "href":"google.com",
      "total":"1" 
     }
     ]
    },
     { "id": 6,
     "name": "HeartBreak Weather" ,
     "owner":[
       {"id":7879,
       "name":"Nial Horran"
       }
       ] ,
     "images":"https://i.scdn.co/image/ab67616d0000b2733d13e91ce05c4e9b3e7201b7",
      "tracks":[
     {
     "href":"google.com",
      "total":"1" 
     }
     ]
    },
     { "id": 7,
     "name": "HeartBreak Weather" ,
     "owner":[
       {"id":7879,
       "name":"Nial Horran"
       }
       ] ,
     "images":"https://i.scdn.co/image/ab67616d0000b2733d13e91ce05c4e9b3e7201b7",
      "tracks":[
     {
     "href":"google.com",
      "total":"1" 
     }
     ]
    },
     { "id": 8,
     "name": "HeartBreak Weather" ,
     "owner":[
       {"id":7879,
       "name":"Nial Horran"
       }
       ] ,
     "images":"https://i.scdn.co/image/ab67616d0000b2733d13e91ce05c4e9b3e7201b7",
      "tracks":[
     {
     "href":"google.com",
      "total":"1" 
     }
     ]
    }
  ],
    "Recents": [
  { "id": 1, "description": "Youmna khaled is Now following you ","time":"10 minutes ago"},
  { "id": 2, "description": "You changed Your password","time":"1 hour ago"},
  { "id": 3, "description": "You created a new playlist","time":"yesterday"},
  { "id": 4, "description": "You created a new playlist","time":"yesterday"},
  { "id": 5, "description": "You created a new playlist","time":"yesterday"},
  { "id": 6, "description": "You created a new playlist","time":"yesterday"}
  ],
  "urlsss":[
    "https://stackoverflow.com/questions/13091433/center-child-divs-inside-parent-div",
    "https://en.wikipedia.org/wiki/Amrish_Puri",
     "https://www.islamicfinder.org/world/egypt/360630/cairo-prayer-times/",
     "https://javascript.info/while-for",
     "https://en.wikipedia.org/wiki/Amplitude_modulation",
      "https://amrdiab.net/",
    "https://www.islamicfinder.org/world/egypt/360630/cairo-prayer-times/",
    "https://amrdiab.net/",
    "https://javascript.info/while-for",
    "https://amrdiab.net/",
    "https://www.islamicfinder.org/world/egypt/360630/cairo-prayer-times/",
    "https://amrdiab.net/",
    "https://javascript.info/while-for",
    "https://javascript.info/while-for"
    ],
    "urls": [
        {
            "url": "https://stackoverflow.com/questions/13091433/center-child-divs-inside-parent-div"
        },
        {
            "url": "https://en.wikipedia.org/wiki/Amrish_Puri"
        },
        {
            "url": "https://www.islamicfinder.org/world/egypt/360630/cairo-prayer-times/"
        },
        {
             "url" : "https://www.islamicfinder.org/world/egypt/360630/cairo-prayer-times/"
        },
        { 
           "url" : "https://amrdiab.net/"
        },
        {
           "url" : "https://javascript.info/while-for"
        }
    ]
}
